[
  {
    "id": "nt-bundle",
    "name": "1NT Responses",
    "memberIds": [
      "stayman",
      "jacoby-transfers",
      "smolen"
    ],
    "systemProfile": {
      "profileId": "1nt-sayc",
      "baseSystem": "sayc",
      "systemConfig": {
        "systemId": "sayc",
        "displayName": "Standard American Yellow Card",
        "ntOpening": {
          "minHcp": 15,
          "maxHcp": 17
        },
        "responderThresholds": {
          "inviteMin": 8,
          "inviteMax": 9,
          "gameMin": 10,
          "slamMin": 15,
          "inviteMinTp": {
            "trump": 8
          },
          "inviteMaxTp": {
            "trump": 10
          },
          "gameMinTp": {
            "trump": 10
          },
          "slamMinTp": {
            "trump": 16
          }
        },
        "openerRebid": {
          "notMinimum": 16,
          "notMinimumTp": {
            "trump": 16
          }
        },
        "interference": {
          "redoubleMin": 10
        },
        "suitResponse": {
          "twoLevelMin": 10,
          "twoLevelForcingDuration": "one-round"
        },
        "oneNtResponseAfterMajor": {
          "forcing": "non-forcing",
          "maxHcp": 10,
          "minHcp": 6
        },
        "openingRequirements": {
          "majorSuitMinLength": 5
        },
        "dontOvercall": {
          "minHcp": 8,
          "maxHcp": 15
        }
      },
      "modules": [
        {
          "moduleId": "stayman",
          "kind": "add-on",
          "attachments": [
            {
              "whenAuction": {
                "kind": "sequence",
                "calls": [
                  "1NT"
                ]
              },
              "requiresCapabilities": [
                "opening.1nt"
              ]
            }
          ]
        },
        {
          "moduleId": "jacoby-transfers",
          "kind": "add-on",
          "attachments": [
            {
              "whenAuction": {
                "kind": "sequence",
                "calls": [
                  "1NT"
                ]
              },
              "requiresCapabilities": [
                "opening.1nt"
              ]
            }
          ]
        },
        {
          "moduleId": "smolen",
          "kind": "add-on",
          "attachments": [
            {
              "whenAuction": {
                "kind": "sequence",
                "calls": [
                  "1NT"
                ]
              },
              "requiresCapabilities": [
                "opening.1nt"
              ]
            }
          ]
        }
      ]
    },
    "declaredCapabilities": {
      "opening.1nt": "active"
    },
    "category": "Constructive",
    "description": "Full 1NT response system with Stayman, Jacoby Transfers, Smolen, and natural bids",
    "teaching": {
      "purpose": "Find the best contract after partner opens 1NT: major-suit fit via Stayman, transfers, or Smolen, or notrump game/invite",
      "whenToUse": "Partner opens 1NT (15-17 HCP balanced). You choose between Stayman (4-card major, 8+ HCP), Jacoby Transfer (5+ card major), Smolen (5-4 in majors, game values — bid Stayman then show pattern), or natural NT bids (no major).",
      "whenNotToUse": [
        "0-7 HCP with no 5-card major — pass",
        "5+ card major with no 4-card in the other major — use transfer, not Stayman",
        "5-4 in majors with invite values (8-9 HCP) — use Stayman, then show the 5-card major after 2D denial",
        "4333 shape with 8-9 HCP — 2NT invite may be better than Stayman"
      ],
      "tradeoff": "Artificial bids (2♣ Stayman, 2♦/2♥ transfers, Smolen 3H/3S) give up natural meanings of those bids",
      "principle": "Finding an 8-card major fit is worth more than notrump; Stayman, transfers, and Smolen are tools to find that fit while keeping the strong hand as declarer",
      "roles": "Responder is captain after 1NT — opener describes, responder decides the final contract"
    }
  },
  {
    "id": "strong-2c-bundle",
    "name": "Strong 2♣",
    "memberIds": [
      "strong-2c",
      "stayman",
      "jacoby-transfers"
    ],
    "systemProfile": {
      "profileId": "strong-2c-sayc",
      "baseSystem": "sayc",
      "modules": [
        {
          "moduleId": "strong-2c",
          "kind": "add-on",
          "attachments": []
        },
        {
          "moduleId": "stayman",
          "kind": "add-on",
          "attachments": [
            {
              "whenAuction": {
                "kind": "sequence",
                "calls": [
                  "2C",
                  "2D",
                  "2NT"
                ]
              },
              "requiresCapabilities": []
            }
          ]
        },
        {
          "moduleId": "jacoby-transfers",
          "kind": "add-on",
          "attachments": [
            {
              "whenAuction": {
                "kind": "sequence",
                "calls": [
                  "2C",
                  "2D",
                  "2NT"
                ]
              },
              "requiresCapabilities": []
            }
          ]
        }
      ]
    },
    "category": "Constructive",
    "description": "Open 2C with a hand too strong for a one-level opening, then use waiting and positive-suit responses to keep the auction organized.",
    "teaching": {
      "purpose": "Open very strong hands with an artificial 2C bid, then use the waiting or positive-suit structure to describe shape.",
      "whenToUse": "Open 2C with a balanced 22+ count or an unbalanced hand with roughly 9+ playing tricks. As responder, bid 2D waiting unless you have 8+ HCP and a good 5+ suit.",
      "whenNotToUse": [
        "With 20-21 balanced HCP — open 2NT instead",
        "With a weak hand and a long suit — use a Weak Two instead",
        "2C is always artificial here — never open 2C to show clubs"
      ],
      "tradeoff": "2C loses its natural club meaning in exchange for a forcing opening that prevents being passed out with a monster hand.",
      "principle": "Start with the waiting 2D reply unless responder has real suit quality; opener then clarifies balanced versus natural-suit routes. After 2C-2D-2NT, continue with ordinary NT methods (Stayman and Jacoby transfers).",
      "roles": "Opener describes the monster; responder decides whether to drive to game, slam, or settle."
    }
  }
]
